nsscurves/__init__.py
nsscurves/nss.py
nsscurves/test.py
nsscurves-2022.7.22.dist-info/LICENSE
nsscurves-2022.7.22.dist-info/METADATA
nsscurves-2022.7.22.dist-info/WHEEL
nsscurves-2022.7.22.dist-info/top_level.txt
nsscurves-2022.7.22.dist-info/RECORD
