Metadata-Version: 2.1
Name: nsscurves
Version: 2022.7.22
Summary: Modelo Nelson Siegel Svensson.
Home-page: https://github.com/mfhorita
Author: Marcelo Horita
Author-email: mfhorita@gmail.com.br
License: MIT License
Keywords: nss nelson siegel svensson curves
Platform: UNKNOWN
Classifier: License :: Freeware
Classifier: Programming Language :: Python
Classifier: Operating System :: OS Independent
Classifier: Development Status :: 5 - Production/Stable
Classifier: Natural Language :: Portuguese (Brazilian)
Classifier: Intended Audience :: Developers
Classifier: Topic :: Utilities
License-File: LICENSE
